maxcube_mqtt-0.0.4.data/scripts/maxcube-mqtt
maxcube_mqtt-0.0.4.dist-info/DESCRIPTION.rst
maxcube_mqtt-0.0.4.dist-info/METADATA
maxcube_mqtt-0.0.4.dist-info/RECORD
maxcube_mqtt-0.0.4.dist-info/WHEEL
maxcube_mqtt-0.0.4.dist-info/metadata.json
maxcube_mqtt-0.0.4.dist-info/top_level.txt
maxcubemqtt/__init__.py
maxcubemqtt/server.py
