Metadata-Version: 2.0
Name: maxcube-mqtt
Version: 0.0.4
Summary: Control your eQ-3/ELV MAX! Cube with MQTT
Home-page: https://github.com/goodfield/maxcube-mqtt.git
Author: David Uebelacker
Author-email: david@uebelacker.ch
License: The MIT License (MIT)
Requires-Dist: maxcube-api
Requires-Dist: paho-mqtt
